csc_cyb600_jmdv/__init__.py
csc_cyb600_jmdv/main.py
csc_cyb600_yamacr-1.3.0.data/scripts/say-hello-cyb600
csc_cyb600_yamacr-1.3.0.dist-info/LICENSE
csc_cyb600_yamacr-1.3.0.dist-info/METADATA
csc_cyb600_yamacr-1.3.0.dist-info/WHEEL
csc_cyb600_yamacr-1.3.0.dist-info/top_level.txt
csc_cyb600_yamacr-1.3.0.dist-info/RECORD
