Metadata-Version: 2.2
Name: csc_cyb600_yamacr
Version: 1.3.0
Author: Rasim Yamac
Author-email: yamacr@canisius.edu
License: Apache License Version 2.0
License-File: LICENSE
Requires-Dist: colorama
Dynamic: author
Dynamic: author-email
Dynamic: license
Dynamic: requires-dist
